xchk_regex_strategies/__init__.py
xchk_regex_strategies/apps.py
xchk_regex_strategies/strats.py
xchk_regex_strategies/tests.py
xchk_regex_strategies-0.1.5.dist-info/WHEEL
xchk_regex_strategies-0.1.5.dist-info/METADATA
xchk_regex_strategies-0.1.5.dist-info/RECORD
