Metadata-Version: 2.1
Name: xchk-regex-strategies
Version: 0.1.5
Summary: Checking strategies for xchk based around regular expressions.
License: MIT
Author: Vincent Nys
Author-email: vincentnys@gmail.com
Requires-Python: >=3.7,<4.0
Classifier: License :: OSI Approved :: MIT License
Classifier: Programming Language :: Python :: 3
Classifier: Programming Language :: Python :: 3.7
Classifier: Programming Language :: Python :: 3.8
Classifier: Programming Language :: Python :: 3.9
Requires-Dist: regex (>=2020.7.14,<2021.0.0)
